Workbook

Sheet Datos
A1: ano | B1: categoria | C1: unidades | D1: ingreso | E1: costo | F1: margen
A2: 2022 | B2: Accessories | C2: 1774 | D2: 78652.25 | E2: 31478.364 | F2: 47173.886
A3: 2022 | B3: Active | C3: 1545 | D3: 81771.82 | E3: 34166.045 | F3: 47605.775
A4: 2022 | B4: Blazers & Jackets | C4: 587 | D4: 51724.11 | E4: 19533.645 | F4: 32190.465
A5: 2022 | B5: Clothing Sets | C5: 44 | D5: 3368.46 | E5: 2107.7539 | F5: 1260.7061
A6: 2022 | B6: Dresses | C6: 921 | D6: 75625.9 | E6: 34091.29 | F6: 41534.61
A7: 2022 | B7: Fashion Hoodies & Sweatshirts | C7: 2062 | D7: 111266.22 | E7: 57733.634 | F7: 53532.586
A8: 2022 | B8: Intimates | C8: 2267 | D8: 77406.93 | E8: 41168.763 | F8: 36238.168
A9: 2022 | B9: Jeans | C9: 2267 | D9: 223868.78 | E9: 119959.32 | F9: 103909.46
A10: 2022 | B10: Jumpsuits & Rompers | C10: 154 | D10: 7025.41 | E10: 3746.0304 | F10: 3279.3796
A11: 2022 | B11: Leggings | C11: 576 | D11: 15777.87 | E11: 9487.3675 | F11: 6290.5025
A12: 2022 | B12: Maternity | C12: 884 | D12: 45691.49 | E12: 20214.07 | F12: 25477.42
A13: 2022 | B13: Outerwear & Coats | C13: 1482 | D13: 208583.39 | E13: 93020.291 | F13: 115563.1
... A53: 2023 | B53: Underwear | C53: 2660 | D53: 72885.69 | E53: 34251.14 | F53: 38634.55

Sheet puente
A1: categoria | B1: unidades 2022 | C1: unidades 2023 | D1: margen 2022 | E1: margen 2023 | F1: margen por unidad 2022 | G1: margen por unidad 2023 | H1: participación en unidades 2022 | I1: participación en unidades 2023 | J1: efecto_mezcla | K1: efecto_margen_unidad | L1: var_margen | M1: pct_del_aumento
A2: Outerwear & Coats | B2: =SUMIFS(Datos!$C$2:$C$53,Datos!$A$2:$A$53,2022,Datos!$B$2:$B$53,$A2) -> 1482 | C2: =SUMIFS(Datos!$C$2:$C$53,Datos!$A$2:$A$53,2023,Datos!$B$2:$B$53,$A2) -> 3200 | D2: =SUMIFS(Datos!$F$2:$F$53,Datos!$A$2:$A$53,2022,Datos!$B$2:$B$53,$A2) -> 115563.1 | E2: =SUMIFS(Datos!$F$2:$F$53,Datos!$A$2:$A$53,2023,Datos!$B$2:$B$53,$A2) -> 259617.55 | F2: =+D2/B2 -> 77.977799 | G2: =+E2/C2 -> 81.130484 | H2: =+B2/$B$28 -> 0.046683047 | I2: =+C2/$C$28 -> 0.050104123 | J2: =$C$28*(I2-H2)*F2 -> 17037.67 | K2: =C2*(G2-F2) -> 10088.592 | L2: =+E2-D2 -> 144054.45 | M2: =+L2/$L$28 -> 0.14187131
A3: Jeans | B3: =SUMIFS(Datos!$C$2:$C$53,Datos!$A$2:$A$53,2022,Datos!$B$2:$B$53,$A3) -> 2267 | C3: =SUMIFS(Datos!$C$2:$C$53,Datos!$A$2:$A$53,2023,Datos!$B$2:$B$53,$A3) -> 4483 | D3: =SUMIFS(Datos!$F$2:$F$53,Datos!$A$2:$A$53,2022,Datos!$B$2:$B$53,$A3) -> 103909.46 | E3: =SUMIFS(Datos!$F$2:$F$53,Datos!$A$2:$A$53,2023,Datos!$B$2:$B$53,$A3) -> 205612.44 | F3: =+D3/B3 -> 45.835667 | G3: =+E3/C3 -> 45.864921 | H3: =+B3/$B$28 -> 0.071410571 | I3: =+C3/$C$28 -> 0.070192744 | J3: =$C$28*(I3-H3)*F3 -> -3565.0507 | K3: =C3*(G3-F3) -> 131.14748 | L3: =+E3-D3 -> 101702.99 | M3: =+L3/$L$28 -> 0.10016168
A4: Sweaters | B4: =SUMIFS(Datos!$C$2:$C$53,Datos!$A$2:$A$53,2022,Datos!$B$2:$B$53,$A4) -> 1984 | C4: =SUMIFS(Datos!$C$2:$C$53,Datos!$A$2:$A$53,2023,Datos!$B$2:$B$53,$A4) -> 3931 | D4: =SUMIFS(Datos!$F$2:$F$53,Datos!$A$2:$A$53,2022,Datos!$B$2:$B$53,$A4) -> 75463.935 | E4: =SUMIFS(Datos!$F$2:$F$53,Datos!$A$2:$A$53,2023,Datos!$B$2:$B$53,$A4) -> 156016.75 | F4: =+D4/B4 -> 38.036258 | G4: =+E4/C4 -> 39.688821 | H4: =+B4/$B$28 -> 0.062496062 | I4: =+C4/$C$28 -> 0.061549783 | J4: =$C$28*(I4-H4)*F4 -> -2298.7602 | K4: =C4*(G4-F4) -> 6496.2258 | L4: =+E4-D4 -> 80552.82 | M4: =+L4/$L$28 -> 0.079332045
A5: Suits & Sport Coats | B5: =SUMIFS(Datos!$C$2:$C$53,Datos!$A$2:$A$53,2022,Datos!$B$2:$B$53,$A5) -> 881 | C5: =SUMIFS(Datos!$C$2:$C$53,Datos!$A$2:$A$53,2023,Datos!$B$2:$B$53,$A5) -> 1829 | D5: =SUMIFS(Datos!$F$2:$F$53,Datos!$A$2:$A$53,2022,Datos!$B$2:$B$53,$A5) -> 65625.048 | E5: =SUMIFS(Datos!$F$2:$F$53,Datos!$A$2:$A$53,2023,Datos!$B$2:$B$53,$A5) -> 138941.13 | F5: =+D5/B5 -> 74.489271 | G5: =+E5/C5 -> 75.965625 | H5: =+B5/$B$28 -> 0.027751528 | I5: =+C5/$C$28 -> 0.028637638 | J5: =$C$28*(I5-H5)*F5 -> 4215.5845 | K5: =C5*(G5-F5) -> 2700.2525 | L5: =+E5-D5 -> 73316.081 | M5: =+L5/$L$28 -> 0.072204979
A6: Fashion Hoodies & Sweatshirts | B6: =SUMIFS(Datos!$C$2:$C$53,Datos!$A$2:$A$53,2022,Datos!$B$2:$B$53,$A6) -> 2062 | C6: =SUMIFS(Datos!$C$2:$C$53,Datos!$A$2:$A$53,2023,Datos!$B$2:$B$53,$A6) -> 4133 | D6: =SUMIFS(Datos!$F$2:$F$53,Datos!$A$2:$A$53,2022,Datos!$B$2:$B$53,$A6) -> 53532.586 | E6: =SUMIFS(Datos!$F$2:$F$53,Datos!$A$2:$A$53,2023,Datos!$B$2:$B$53,$A6) -> 109529.11 | F6: =+D6/B6 -> 25.961487 | G6: =+E6/C6 -> 26.501115 | H6: =+B6/$B$28 -> 0.064953065 | I6: =+C6/$C$28 -> 0.064712606 | J6: =$C$28*(I6-H6)*F6 -> -398.70092 | K6: =C6*(G6-F6) -> 2230.2838 | L6: =+E6-D6 -> 55996.523 | M6: =+L6/$L$28 -> 0.055147898
A7: Dresses | B7: =SUMIFS(Datos!$C$2:$C$53,Datos!$A$2:$A$53,2022,Datos!$B$2:$B$53,$A7) -> 921 | C7: =SUMIFS(Datos!$C$2:$C$53,Datos!$A$2:$A$53,2023,Datos!$B$2:$B$53,$A7) -> 1970 | D7: =SUMIFS(Datos!$F$2:$F$53,Datos!$A$2:$A$53,2022,Datos!$B$2:$B$53,$A7) -> 41534.61 | E7: =SUMIFS(Datos!$F$2:$F$53,Datos!$A$2:$A$53,2023,Datos!$B$2:$B$53,$A7) -> 94376.13 | F7: =+D7/B7 -> 45.097297 | G7: =+E7/C7 -> 47.906665 | H7: =+B7/$B$28 -> 0.029011529 | I7: =+C7/$C$28 -> 0.03084535 | J7: =$C$28*(I7-H7)*F7 -> 5281.8259 | K7: =C7*(G7-F7) -> 5534.4557 | L7: =+E7-D7 -> 52841.52 | M7: =+L7/$L$28 -> 0.052040709
A8: Swim | B8: =SUMIFS(Datos!$C$2:$C$53,Datos!$A$2:$A$53,2022,Datos!$B$2:$B$53,$A8) -> 2055 | C8: =SUMIFS(Datos!$C$2:$C$53,Datos!$A$2:$A$53,2023,Datos!$B$2:$B$53,$A8) -> 4019 | D8: =SUMIFS(Datos!$F$2:$F$53,Datos!$A$2:$A$53,2022,Datos!$B$2:$B$53,$A8) -> 58618.246 | E8: =SUMIFS(Datos!$F$2:$F$53,Datos!$A$2:$A$53,2023,Datos!$B$2:$B$53,$A8) -> 109406.58 | F8: =+D8/B8 -> 28.524694 | G8: =+E8/C8 -> 27.222339 | H8: =+B8/$B$28 -> 0.064732565 | I8: =+C8/$C$28 -> 0.062927647 | J8: =$C$28*(I8-H8)*F8 -> -3288.1758 | K8: =C8*(G8-F8) -> -5234.1633 | L8: =+E8-D8 -> 50788.335 | M8: =+L8/$L$28 -> 0.05001864
A9: Sleep & Lounge | B9: =SUMIFS(Datos!$C$2:$C$53,Datos!$A$2:$A$53,2022,Datos!$B$2:$B$53,$A9) -> 1931 | C9: =SUMIFS(Datos!$C$2:$C$53,Datos!$A$2:$A$53,2023,Datos!$B$2:$B$53,$A9) -> 3861 | D9: =SUMIFS(Datos!$F$2:$F$53,Datos!$A$2:$A$53,2022,Datos!$B$2:$B$53,$A9) -> 48806.515 | E9: =SUMIFS(Datos!$F$2:$F$53,Datos!$A$2:$A$53,2023,Datos!$B$2:$B$53,$A9) -> 97121.914 | F9: =+D9/B9 -> 25.275254 | G9: =+E9/C9 -> 25.154601 | H9: =+B9/$B$28 -> 0.060826561 | I9: =+C9/$C$28 -> 0.060453755 | J9: =$C$28*(I9-H9)*F9 -> -601.80278 | K9: =C9*(G9-F9) -> -465.83997 | L9: =+E9-D9 -> 48315.399 | M9: =+L9/$L$28 -> 0.047583182
A10: Active | B10: =SUMIFS(Datos!$C$2:$C$53,Datos!$A$2:$A$53,2022,Datos!$B$2:$B$53,$A10) -> 1545 | C10: =SUMIFS(Datos!$C$2:$C$53,Datos!$A$2:$A$53,2023,Datos!$B$2:$B$53,$A10) -> 3237 | D10: =SUMIFS(Datos!$F$2:$F$53,Datos!$A$2:$A$53,2022,Datos!$B$2:$B$53,$A10) -> 47605.775 | E10: =SUMIFS(Datos!$F$2:$F$53,Datos!$A$2:$A$53,2023,Datos!$B$2:$B$53,$A10) -> 95903.302 | F10: =+D10/B10 -> 30.8128 | G10: =+E10/C10 -> 29.627217 | H10: =+B10/$B$28 -> 0.048667549 | I10: =+C10/$C$28 -> 0.050683452 | J10: =$C$28*(I10-H10)*F10 -> 3967.1377 | K10: =C10*(G10-F10) -> -3837.7303 | L10: =+E10-D10 -> 48297.527 | M10: =+L10/$L$28 -> 0.04756558
A11: Shorts | B11: =SUMIFS(Datos!$C$2:$C$53,Datos!$A$2:$A$53,2022,Datos!$B$2:$B$53,$A11) -> 1917 | C11: =SUMIFS(Datos!$C$2:$C$53,Datos!$A$2:$A$53,2023,Datos!$B$2:$B$53,$A11) -> 3850 | D11: =SUMIFS(Datos!$F$2:$F$53,Datos!$A$2:$A$53,2022,Datos!$B$2:$B$53,$A11) -> 43760.883 | E11: =SUMIFS(Datos!$F$2:$F$53,Datos!$A$2:$A$53,2023,Datos!$B$2:$B$53,$A11) -> 88849.252 | F11: =+D11/B11 -> 22.827795 | G11: =+E11/C11 -> 23.077728 | H11: =+B11/$B$28 -> 0.06038556 | I11: =+C11/$C$28 -> 0.060281523 | J11: =$C$28*(I11-H11)*F11 -> -151.68123 | K11: =C11*(G11-F11) -> 962.24142 | L11: =+E11-D11 -> 45088.369 | M11: =+L11/$L$28 -> 0.044405057
A12: Pants | B12: =SUMIFS(Datos!$C$2:$C$53,Datos!$A$2:$A$53,2022,Datos!$B$2:$B$53,$A12) -> 1311 | C12: =SUMIFS(Datos!$C$2:$C$53,Datos!$A$2:$A$53,2023,Datos!$B$2:$B$53,$A12) -> 2529 | D12: =SUMIFS(Datos!$F$2:$F$53,Datos!$A$2:$A$53,2022,Datos!$B$2:$B$53,$A12) -> 40936.629 | E12: =SUMIFS(Datos!$F$2:$F$53,Datos!$A$2:$A$53,2023,Datos!$B$2:$B$53,$A12) -> 82508.611 | F12: =+D12/B12 -> 31.225499 | G12: =+E12/C12 -> 32.624994 | H12: =+B12/$B$28 -> 0.041296541 | I12: =+C12/$C$28 -> 0.039597914 | J12: =$C$28*(I12-H12)*F12 -> -3387.5358 | K12: =C12*(G12-F12) -> 3539.3237 | L12: =+E12-D12 -> 41571.982 | M12: =+L12/$L$28 -> 0.04094196
A13: Intimates | B13: =SUMIFS(Datos!$C$2:$C$53,Datos!$A$2:$A$53,2022,Datos!$B$2:$B$53,$A13) -> 2267 | C13: =SUMIFS(Datos!$C$2:$C$53,Datos!$A$2:$A$53,2023,Datos!$B$2:$B$53,$A13) -> 4774 | D13: =SUMIFS(Datos!$F$2:$F$53,Datos!$A$2:$A$53,2022,Datos!$B$2:$B$53,$A13) -> 36238.168 | E13: =SUMIFS(Datos!$F$2:$F$53,Datos!$A$2:$A$53,2023,Datos!$B$2:$B$53,$A13) -> 77384.797 | F13: =+D13/B13 -> 15.985076 | G13: =+E13/C13 -> 16.209635 | H13: =+B13/$B$28 -> 0.071410571 | I13: =+C13/$C$28 -> 0.074749088 | J13: =$C$28*(I13-H13)*F13 -> 3408.3545 | K13: =C13*(G13-F13) -> 1072.0433 | L13: =+E13-D13 -> 41146.629 | M13: =+L13/$L$28 -> 0.040523054
... A27: Clothing Sets | B27: =SUMIFS(Datos!$C$2:$C$53,Datos!$A$2:$A$53,2022,Datos!$B$2:$B$53,$A27) -> 44 | C27: =SUMIFS(Datos!$C$2:$C$53,Datos!$A$2:$A$53,2023,Datos!$B$2:$B$53,$A27) -> 63 | D27: =SUMIFS(Datos!$F$2:$F$53,Datos!$A$2:$A$53,2022,Datos!$B$2:$B$53,$A27) -> 1260.7061 | E27: =SUMIFS(Datos!$F$2:$F$53,Datos!$A$2:$A$53,2023,Datos!$B$2:$B$53,$A27) -> 2111.816 | F27: =+D27/B27 -> 28.652412 | G27: =+E27/C27 -> 33.520889 | H27: =+B27/$B$28 -> 0.0013860014 | I27: =+C27/$C$28 -> 0.00098642491 | J27: =$C$28*(I27-H27)*F27 -> -731.2024 | K27: =C27*(G27-F27) -> 306.71408 | L27: =+E27-D27 -> 851.1099 | M27: =+L27/$L$28 -> 0.00083821137
A28: TOTAL | B28: =SUM(B2:B27) -> 31746 | C28: =SUM(C2:C27) -> 63867 | D28: =SUM(D2:D27) -> 968260.41 | E28: =SUM(E2:E27) -> 1983648.6 | F28: =+D28/B28 -> 30.500233 | G28: =+E28/C28 -> 31.059054 | H28: =SUM(H2:H27) -> 1 | I28: =SUM(I2:I27) -> 1 | J28: =SUM(J2:J27) -> 12378.629 | K28: =SUM(K2:K27) -> 23311.539 | L28: =+E28-D28 -> 1015388.2 | M28: =SUM(M2:M27) -> 1
A31: Margen 2022 | B31: =+D28 -> 968260.41
A32: Efecto volumen | B32: =(C28-B28)*F28 -> 979698
A33: Efecto mezcla | B33: =+J28 -> 12378.629
A34: Efecto margen por unidad | B34: =+K28 -> 23311.539
A35: Margen 2023 (calculado) | B35: =+B31+B32+B33+B34 -> 1983648.6
A36: Control (tiene que dar 0) | B36: =+B35-E28 -> 0

Sheet Adquisicion
A1: Parámetro | B1: Valor | C1: Tipo
A2: Margen por unidad vendida (2023) | B2: =+puente!G28 -> 31.059054 | C2: Dato
A3: Unidades por cliente nuevo en 12 meses | B3: 1.8 | C3: Supuesto
A4: LTV 12 meses por cliente | B4: =+B2*B3 -> 55.906296 | C4: Calculo
A5: Clientes nuevos 2023 (estimado) | B5: =+puente!C28/Adquisicion!B3 -> 35481.667 | C5: Calculo
A7: Canal | B7: % clientes nuevos | C7: clientes nuevos | D7: Inversión | E7: CAC | F7: Tipo | G7: Fuente | H7: LTV/CAC | I7: Margen neto por cliente
A8: Search | B8: 0.35 | C8: =+$B$5*B8 -> 12418.583 | D8: 370000 | E8: =+D8/C8 -> 29.794059 | F8: Supuesto | G8: Estimación propia | H8: =+$B$4/E8 -> 1.8764243 | I8: =+$B$4-E8 -> 26.112238
A9: Organic | B9: 0.3 | C9: =+$B$5*B9 -> 10644.5 | D9: 55000 | E9: =+D9/C9 -> 5.1669876 | F9: Supuesto | G9: Estimación propia | H9: =+$B$4/E9 -> 10.819901 | I9: =+$B$4-E9 -> 50.739309
A10: Facebook | B10: 0.15 | C10: =+$B$5*B10 -> 5322.25 | D10: 185000 | E10: =+D10/C10 -> 34.759735 | F10: Supuesto | G10: Estimación propia | H10: =+$B$4/E10 -> 1.6083637 | I10: =+$B$4-E10 -> 21.146561
A11: Email | B11: 0.1 | C11: =+$B$5*B11 -> 3548.1667 | D11: 35000 | E11: =+D11/C11 -> 9.8642491 | F11: Supuesto | G11: Estimación propia | H11: =+$B$4/E11 -> 5.6675674 | I11: =+$B$4-E11 -> 46.042047
A12: Display | B12: 0.1 | C12: =+$B$5*B12 -> 3548.1667 | D12: 90000 | E12: =+D12/C12 -> 25.365212 | F12: Supuesto | G12: Estimación propia | H12: =+$B$4/E12 -> 2.204054 | I12: =+$B$4-E12 -> 30.541084
A13: TOTAL | B13: =SUM(B8:B12) -> 1 | C13: =SUM(C8:C12) -> 35481.667

Sheet Escenarios
A1: Parámetro | B1: Pesimista | C1: Base | D1: Optimista
A2: Unidades por cliente en 12 meses | B2: 1.4 | C2: =Adquisicion!B3 -> 1.8 | D2: 2.2
A3: Multiplicador del CAC | B3: 1.3 | C3: 1 | D3: 0.8
A4: LTV 12 meses | B4: =Adquisicion!$B$2*Escenarios!B2 -> 43.482675 | C4: =Adquisicion!$B$2*Escenarios!C2 -> 55.906296 | D4: =Adquisicion!$B$2*Escenarios!D2 -> 68.329918
A5: Umbral LTV/CAC para invertir | B5: 3 | C5: 3 | D5: 3
A7: LTV/CAC por canal en cada escenario
A8: Canal | B8: CAC base | C8: Pesimista | D8: Base | E8: Optimista | F8: Escenarios que superan el umbral | G8: Decisión | H8: inversión | I8: % del presupuesto | J8: CAC máximo para llegar al umbral | K8: reducción de CAC necesaria | L8: unidades por cliente necesarias
A9: =Adquisicion!A8 -> Search | B9: =Adquisicion!E8 -> 29.794059 | C9: =B$4/($B9*B$3) -> 1.122647 | D9: =C$4/($B9*C$3) -> 1.8764243 | E9: =D$4/($B9*D$3) -> 2.8667594 | F9: =COUNTIF(C9:E9,">="&$B$5) -> 0 | G9: =IF(F9=3,"Escalar",IF(F9=0,"Recortar","Probar con tope")) -> Recortar | H9: =+Adquisicion!D8 -> 370000 | I9: =H9/SUM(H$9:H$13) -> 0.50340136 | J9: =+$C$4/$B$5 -> 18.635432 | K9: =MAX(0,1-J9/B9) -> 0.37452522 | L9: =+$B$5*B9/Adquisicion!$B$2 -> 2.8778139
A10: =Adquisicion!A9 -> Organic | B10: =Adquisicion!E9 -> 5.1669876 | C10: =B$4/($B10*B$3) -> 6.4734452 | D10: =C$4/($B10*C$3) -> 10.819901 | E10: =D$4/($B10*D$3) -> 16.530405 | F10: =COUNTIF(C10:E10,">="&$B$5) -> 3 | G10: =IF(F10=3,"Escalar",IF(F10=0,"Recortar","Probar con tope")) -> Escalar | H10: =+Adquisicion!D9 -> 55000 | I10: =H10/SUM(H$9:H$13) -> 0.074829932 | J10: =+$C$4/$B$5 -> 18.635432 | K10: =MAX(0,1-J10/B10) -> 0 | L10: =+$B$5*B10/Adquisicion!$B$2 -> 0.49908034
A11: =Adquisicion!A10 -> Facebook | B11: =Adquisicion!E10 -> 34.759735 | C11: =B$4/($B11*B$3) -> 0.96226889 | D11: =C$4/($B11*C$3) -> 1.6083637 | E11: =D$4/($B11*D$3) -> 2.4572223 | F11: =COUNTIF(C11:E11,">="&$B$5) -> 0 | G11: =IF(F11=3,"Escalar",IF(F11=0,"Recortar","Probar con tope")) -> Recortar | H11: =+Adquisicion!D10 -> 185000 | I11: =H11/SUM(H$9:H$13) -> 0.25170068 | J11: =+$C$4/$B$5 -> 18.635432 | K11: =MAX(0,1-J11/B11) -> 0.46387876 | L11: =+$B$5*B11/Adquisicion!$B$2 -> 3.3574495
A12: =Adquisicion!A11 -> Email | B12: =Adquisicion!E11 -> 9.8642491 | C12: =B$4/($B12*B$3) -> 3.3908523 | D12: =C$4/($B12*C$3) -> 5.6675674 | E12: =D$4/($B12*D$3) -> 8.6587835 | F12: =COUNTIF(C12:E12,">="&$B$5) -> 3 | G12: =IF(F12=3,"Escalar",IF(F12=0,"Recortar","Probar con tope")) -> Escalar | H12: =+Adquisicion!D11 -> 35000 | I12: =H12/SUM(H$9:H$13) -> 0.047619048 | J12: =+$C$4/$B$5 -> 18.635432 | K12: =MAX(0,1-J12/B12) -> 0 | L12: =+$B$5*B12/Adquisicion!$B$2 -> 0.95278974
A13: =Adquisicion!A12 -> Display | B13: =Adquisicion!E12 -> 25.365212 | C13: =B$4/($B13*B$3) -> 1.3186648 | D13: =C$4/($B13*C$3) -> 2.204054 | E13: =D$4/($B13*D$3) -> 3.3673047 | F13: =COUNTIF(C13:E13,">="&$B$5) -> 1 | G13: =IF(F13=3,"Escalar",IF(F13=0,"Recortar","Probar con tope")) -> Probar con tope | H13: =+Adquisicion!D12 -> 90000 | I13: =H13/SUM(H$9:H$13) -> 0.12244898 | J13: =+$C$4/$B$5 -> 18.635432 | K13: =MAX(0,1-J13/B13) -> 0.26531534 | L13: =+$B$5*B13/Adquisicion!$B$2 -> 2.4500307
A15: Resumen por decisión
A16: Decisión | B16: Inversión | C16: % del presupuesto
A17: Recortar | B17: =SUMIF($G$9:$G$13,A17,$H$9:$H$13) -> 555000 | C17: =+B17/SUM(B$17:B$19) -> 0.75510204
A18: Probar con tope | B18: =SUMIF($G$9:$G$13,A18,$H$9:$H$13) -> 90000 | C18: =+B18/SUM(B$17:B$19) -> 0.12244898
A19: Escalar | B19: =SUMIF($G$9:$G$13,A19,$H$9:$H$13) -> 90000 | C19: =+B19/SUM(B$17:B$19) -> 0.12244898

Sheet Resumen
A1: ¿De dónde vino el margen de 2023 y dónde conviene invertir en 2024?
A3: Pregunta: La tienda duplicó su margen entre 2022 y 2023. ¿Qué lo explica y cuánto conviene pagar por seguir adquiriendo clientes?
A5: Hallazgo (datos del dataset)
A6: Margen 2022 | B6: =puente!D28 -> 968260.41
A7: Margen 2023 | B7: =puente!E28 -> 1983648.6
A8: Variación | B8: =+B7/B6-1 -> 1.0486726
A9: % del aumento por volumen | B9: =puente!B32/(puente!E28-puente!D28) -> 0.96485072
A10: % del aumento por mezcla de categorías | B10: =puente!B33/(puente!E28-puente!D28) -> 0.012191032
A11: % del aumento por margen por unidad | B11: =puente!B34/(puente!E28-puente!D28) -> 0.022958253
A12: Categoría que más aportó | B12: =puente!A2 -> Outerwear & Coats
A13: % del aumento de esa categoría | B13: =puente!M2 -> 0.14187131
A14: % del aumento de las 5 mayores | B14: =SUM(puente!M2:M6) -> 0.44871792
A17: Recomendación
A18: 1) No reasignar presupuesto todavía: primero medir el CAC real por canal y las unidades por cliente reales, que son los dos números que cambian la conclusión. 2) Organic y Email superan LTV/CAC de 3 en los tres escenarios, pero dependen del tamaño de la audiencia: hay que cuidarlos, no se escalan con presupuesto. 3) Search y Facebook concentran el 75 % del presupuesto supuesto y no llegan al umbral en ningún escenario. Llegarían con un CAC 37 % y 46 % menor, o con 2,9 y 3,4 unidades por cliente. 4) Display: probar con un tope de inversión y decidir con los resultados reales.
A25: Riesgos y limitaciones
A26: El CAC y la inversión por canal son supuestos: el dataset no trae gasto en marketing. Las unidades por cliente (1,8) son un supuesto. Con otro valor cambia el LTV de todos los canales. Se asume que todas las ventas de 2023 son de clientes nuevos. Eso sobreestima los clientes nuevos y por lo tanto subestima el CAC: la realidad sería peor para los canales pagos. El umbral de 3 es una regla práctica. Un LTV/CAC mayor a 1 igual recupera el costo en 12 meses; solo Facebook en el escenario pesimista (0,96) no lo hace. El LTV mide solo los primeros 12 meses y no incluye compras posteriores. Los datos del dataset son sintéticos.
A34: Que Validar
A35: Gasto real y clientes nuevos por canal, para calcular el CAC real.
A36: Unidades por cliente en los primeros 12 meses, desde el historial de compras.
A37: Capacidad de crecimiento de Organic y Email.
